crawlerdetect/__init__.py
crawlerdetect/__main__.py
crawlerdetect/src/__init__.py
crawlerdetect/src/crawlerdetect.py
crawlerdetect/src/providers/__init__.py
crawlerdetect/src/providers/base.py
crawlerdetect/src/providers/crawlers.py
crawlerdetect/src/providers/exclusions.py
crawlerdetect/src/providers/headers.py
crawlerdetect_coreteam-0.1.5.dist-info/LICENSE
crawlerdetect_coreteam-0.1.5.dist-info/METADATA
crawlerdetect_coreteam-0.1.5.dist-info/WHEEL
crawlerdetect_coreteam-0.1.5.dist-info/top_level.txt
crawlerdetect_coreteam-0.1.5.dist-info/zip-safe
crawlerdetect_coreteam-0.1.5.dist-info/RECORD
